parserlib/__init__.py
parserlib/__main__.py
parserlib/lexer.py
parserlib/parser.py
parserlib/token.py
parserlib-0.1.1.dist-info/LICENSE
parserlib-0.1.1.dist-info/METADATA
parserlib-0.1.1.dist-info/WHEEL
parserlib-0.1.1.dist-info/RECORD
