Metadata-Version: 2.1
Name: parserlib
Version: 0.1.1
Summary: A Pythonic parser implementation!
Home-page: https://github.com/GrandMoff100/parserlib
Author: Nate
Author-email: minecraftcrusher100@gmail.com
Requires-Python: >=3.10,<4.0
Classifier: Programming Language :: Python :: 3
Classifier: Programming Language :: Python :: 3.10
Classifier: Programming Language :: Python :: 3.11
Classifier: Programming Language :: Python :: 3.12
Project-URL: Repository, https://github.com/GrandMoff100/parserlib
